mormiz-0.5.3.dist-info/METADATA
mormiz-0.5.3.dist-info/WHEEL
mormiz-0.5.3.dist-info/license_files/LICENSE
mormiz/__init__.py
mormiz/mormiz.py
mormiz/test.ipynb
mormiz/tokenizer
mormiz/mormiz.cpython-312-darwin.so
mormiz-0.5.3.dist-info/RECORD
