Metadata-Version: 2.3
Name: mormiz
Version: 0.5.3
Classifier: Programming Language :: Rust
Classifier: Programming Language :: Python :: Implementation :: CPython
Classifier: Programming Language :: Python :: Implementation :: PyPy
License-File: LICENSE
Summary: mormiz is a an Arabic Tokenizer
Requires-Python: >=3.8
